smax/__init__.py
smax/__main__.py
smax/__version__.py
smax/asyncio_reactor.py
smax/glfw_reactor.py
smax/log.py
smax/parser.py
smax/qt5.py
smax/reactor.py
smax/select_reactor.py
smax/translate.py
smax_dsl-1.3.0.dist-info/LICENSE
smax_dsl-1.3.0.dist-info/METADATA
smax_dsl-1.3.0.dist-info/WHEEL
smax_dsl-1.3.0.dist-info/entry_points.txt
smax_dsl-1.3.0.dist-info/top_level.txt
smax_dsl-1.3.0.dist-info/RECORD
