Metadata-Version: 2.1
Name: smax-dsl
Version: 1.3.0
Summary: smax: a DSL for Harel state machines in Python.
Home-page: https://github.com/baymotion/smax
Author: Patrick O'Grady
Author-email: patrick.ogrady.gm@gmail.com
License: GPLv3
Classifier: Development Status :: 4 - Beta
Classifier: Intended Audience :: Developers
Classifier: License :: OSI Approved :: GNU General Public License v3 (GPLv3)
Classifier: Programming Language :: Python
Classifier: Programming Language :: Python :: 3
License-File: LICENSE
Requires-Dist: yapps
Requires-Dist: jinja2
Requires-Dist: pyyaml
